keyword_explorer/__init__.py
keyword_explorer/Apps/AppBase.py
keyword_explorer/Apps/GoogleExplorer.py
keyword_explorer/Apps/KeywordExplorer.py
keyword_explorer/Apps/ModelExplorer.py
keyword_explorer/Apps/TweetCountExplorer.py
keyword_explorer/Apps/TweetDownloader.py
keyword_explorer/Apps/TweetEmbedExplorer.py
keyword_explorer/Apps/WikiPageviewExplorer.py
keyword_explorer/Apps/__init__.py
keyword_explorer/OpenAI/OpenAIComms.py
keyword_explorer/TwitterV2/TweetKeywords.py
keyword_explorer/TwitterV2/TwitterV2Base.py
keyword_explorer/TwitterV2/TwitterV2Counts.py
keyword_explorer/TwitterV2/__init__.py
keyword_explorer/TwitterV2/tweet_lookup.py
keyword_explorer/mastodon/__init__.py
keyword_explorer/mastodon/post_lookup.py
keyword_explorer/tkUtils/Buttons.py
keyword_explorer/tkUtils/CanvasData.py
keyword_explorer/tkUtils/CanvasFrame.py
keyword_explorer/tkUtils/Checkboxes.py
keyword_explorer/tkUtils/ConsoleDprint.py
keyword_explorer/tkUtils/DataField.py
keyword_explorer/tkUtils/DateEntryField.py
keyword_explorer/tkUtils/LabeledParam.py
keyword_explorer/tkUtils/ListField.py
keyword_explorer/tkUtils/MoveableNode.py
keyword_explorer/tkUtils/TextComparePopup.py
keyword_explorer/tkUtils/TextField.py
keyword_explorer/tkUtils/TkCanvasBase.py
keyword_explorer/tkUtils/ToolTip.py
keyword_explorer/tkUtils/TopicCombo.py
keyword_explorer/tkUtils/TopicComboExt.py
keyword_explorer/tkUtils/__init__.py
keyword_explorer/utils/CorporaGenerator.py
keyword_explorer/utils/ManifoldReduction.py
keyword_explorer/utils/MySqlInterface.py
keyword_explorer/utils/SharedObjects.py
keyword_explorer/utils/TextSimilarity.py
keyword_explorer/utils/app_test.py
keyword_explorer/utils/excel_to_latex.py
keyword_explorer/utils/find_transformer_models.py
keyword_explorer/utils/google_search.py
keyword_explorer/utils/wikipedia_search.py
keyword_explorer-0.43a0.dist-info/LICENSE
keyword_explorer-0.43a0.dist-info/METADATA
keyword_explorer-0.43a0.dist-info/WHEEL
keyword_explorer-0.43a0.dist-info/top_level.txt
keyword_explorer-0.43a0.dist-info/RECORD
